{
  "id": "AAC1988",
  "stages": [
    {
      "name": "Group Stage",
      "type": "roundrobin",
      "eliminateCount": 4,
      "next_round": "Semi-finals",
      "advancement": { "teams": { "auto": [1, 2], "eliminated": [3, 4, 5], "text": "The top 2 teams would advance to the Semi-finals." } },
      "groups": [
        {
          "name": "Group A",
          "teams": [{ "id": "IRN" }, { "id": "QAT" }, { "id": "UAE" }, { "id": "KOR" }, { "id": "JPN" }],
          "matches": [
            {
              "home_team": "IRN",
              "away_team": "QAT",
              "home_score": 2,
              "away_score": 0,
              "date": "1988-12-02",
              "time": "16:00",
              "stadium": "Al-Ahly Stadium",
              "city": "Doha"
            },
            {
              "home_team": "UAE",
              "away_team": "KOR",
              "home_score": 0,
              "away_score": 1,
              "date": "1988-12-03",
              "time": "15:00",
              "stadium": "Al-Ahly Stadium",
              "city": "Doha"
            },
            {
              "home_team": "JPN",
              "away_team": "IRN",
              "home_score": 0,
              "away_score": 0,
              "date": "1988-12-04",
              "time": "15:00",
              "stadium": "Qatar SC Stadium",
              "city": "Doha"
            },
            {
              "home_team": "QAT",
              "away_team": "UAE",
              "home_score": 2,
              "away_score": 1,
              "date": "1988-12-05",
              "time": "17:00",
              "stadium": "Qatar SC Stadium",
              "city": "Doha"
            },
            {
              "home_team": "KOR",
              "away_team": "JPN",
              "home_score": 2,
              "away_score": 0,
              "date": "1988-12-06",
              "time": "15:00",
              "stadium": "Qatar SC Stadium",
              "city": "Doha"
            },
            {
              "home_team": "IRN",
              "away_team": "UAE",
              "home_score": 1,
              "away_score": 0,
              "date": "1988-12-08",
              "time": "15:00",
              "stadium": "Qatar SC Stadium",
              "city": "Doha"
            },
            {
              "home_team": "QAT",
              "away_team": "KOR",
              "home_score": 2,
              "away_score": 3,
              "date": "1988-12-09",
              "time": "17:00",
              "stadium": "Qatar SC Stadium",
              "city": "Doha"
            },
            {
              "home_team": "UAE",
              "away_team": "JPN",
              "home_score": 1,
              "away_score": 0,
              "date": "1988-12-10",
              "time": "15:00",
              "stadium": "Al-Ahly Stadium",
              "city": "Doha"
            },
            {
              "home_team": "KOR",
              "away_team": "IRN",
              "home_score": 3,
              "away_score": 0,
              "date": "1988-12-11",
              "time": "17:00",
              "stadium": "Al-Ahly Stadium",
              "city": "Doha"
            },
            {
              "home_team": "JPN",
              "away_team": "QAT",
              "home_score": 0,
              "away_score": 3,
              "date": "1988-12-12",
              "time": "17:00",
              "stadium": "Al-Ahly Stadium",
              "city": "Doha"
            }
          ]
        },
        {
          "name": "Group B",
          "teams": [{ "id": "SYR" }, { "id": "KSA" }, { "id": "KUW" }, { "id": "BHR" }, { "id": "CHN" }],
          "matches": [
            {
              "home_team": "SYR",
              "away_team": "KSA",
              "home_score": 0,
              "away_score": 2,
              "date": "1988-12-02",
              "time": "18:00",
              "stadium": "Qatar SC Stadium",
              "city": "Doha"
            },
            {
              "home_team": "KUW",
              "away_team": "BHR",
              "home_score": 0,
              "away_score": 0,
              "date": "1988-12-03",
              "time": "17:00",
              "stadium": "Al-Ahly Stadium",
              "city": "Doha"
            },
            {
              "home_team": "CHN",
              "away_team": "SYR",
              "home_score": 3,
              "away_score": 0,
              "date": "1988-12-04",
              "time": "17:00",
              "stadium": "Qatar SC Stadium",
              "city": "Doha"
            },
            {
              "home_team": "KSA",
              "away_team": "KUW",
              "home_score": 0,
              "away_score": 0,
              "date": "1988-12-05",
              "time": "15:00",
              "stadium": "Al-Ahly Stadium",
              "city": "Doha"
            },
            {
              "home_team": "BHR",
              "away_team": "CHN",
              "home_score": 0,
              "away_score": 1,
              "date": "1988-12-06",
              "time": "17:00",
              "stadium": "Qatar SC Stadium",
              "city": "Doha"
            },
            {
              "home_team": "SYR",
              "away_team": "KUW",
              "home_score": 1,
              "away_score": 0,
              "date": "1988-12-08",
              "time": "17:00",
              "stadium": "Al-Ahly Stadium",
              "city": "Doha"
            },
            {
              "home_team": "KSA",
              "away_team": "BHR",
              "home_score": 1,
              "away_score": 1,
              "date": "1988-12-09",
              "time": "15:00",
              "stadium": "Qatar SC Stadium",
              "city": "Doha"
            },
            {
              "home_team": "KUW",
              "away_team": "CHN",
              "home_score": 2,
              "away_score": 2,
              "date": "1988-12-10",
              "time": "17:00",
              "stadium": "Al-Ahly Stadium",
              "city": "Doha"
            },
            {
              "home_team": "BHR",
              "away_team": "SYR",
              "home_score": 0,
              "away_score": 1,
              "date": "1988-12-11",
              "time": "15:00",
              "stadium": "Qatar SC Stadium",
              "city": "Doha"
            },
            {
              "home_team": "CHN",
              "away_team": "KSA",
              "home_score": 0,
              "away_score": 1,
              "date": "1988-12-12",
              "time": "15:00",
              "stadium": "Al-Ahly Stadium",
              "city": "Doha"
            }
          ]
        }
      ]
    },
    {
      "name": "Knockout Stage",
      "type": "knockout",
      "rounds": [
        {
          "name": "Semi-finals",
          "short_name": "1/2",
          "eliminateCount": 2,
          "next_round": "Final",
          "matches": [
            {
              "home_team": "KOR",
              "away_team": "CHN",
              "home_score": 0,
              "away_score": 0,
              "home_extra_score": 2,
              "away_extra_score": 1,
              "date": "1988-12-14",
              "time": "16:00",
              "stadium": "Qatar SC Stadium",
              "city": "Doha",
              "bracket_order": 1
            },
            {
              "home_team": "KSA",
              "away_team": "IRN",
              "home_score": 1,
              "away_score": 0,
              "date": "1988-12-15",
              "time": "16:00",
              "stadium": "Qatar SC Stadium",
              "city": "Doha",
              "bracket_order": 2
            }
          ]
        },
        {
          "name": "Third-place",
          "short_name": "3rd",
          "matches": [
            {
              "home_team": "CHN",
              "away_team": "IRN",
              "home_score": 0,
              "away_score": 0,
              "home_penalty_score": 0,
              "away_penalty_score": 3,
              "date": "1988-12-17",
              "time": "16:00",
              "stadium": "Al-Ahly Stadium",
              "city": "Doha"
            }
          ]
        },
        {
          "name": "Final",
          "short_name": "1st",
          "matches": [
            {
              "home_team": "KOR",
              "away_team": "KSA",
              "home_score": 0,
              "away_score": 0,
              "home_extra_score": 0,
              "away_extra_score": 0,
              "home_penalty_score": 3,
              "away_penalty_score": 4,
              "date": "1988-12-18",
              "time": "16:00",
              "stadium": "Al-Ahly Stadium",
              "city": "Doha"
            }
          ]
        }
      ]
    }
  ]
}
