{ "id": "CONFEDC1999", "stages": [ { "name": "Group Stage", "type": "roundrobin", "eliminateCount": 4, "next_round": "Semi-finals", "advancement": { "teams": { "auto": [1, 2], "eliminated": [3, 4], "text": "The top 2 teams would advance to the Semi-finals." } }, "groups": [ { "name": "Group A", "teams": [{ "id": "BOL" }, { "id": "EGY" }, { "id": "MEX" }, { "id": "KSA" }], "matches": [ { "home_team": "BOL", "away_team": "EGY", "home_score": 2, "away_score": 2, "date": "1999-07-25", "time": "12:00", "stadium": "Estadio Azteca", "city": "Mexico City" }, { "home_team": "MEX", "away_team": "KSA", "home_score": 5, "away_score": 1, "date": "1999-07-25", "time": "14:30", "stadium": "Estadio Azteca", "city": "Mexico City" }, { "home_team": "KSA", "away_team": "BOL", "home_score": 0, "away_score": 0, "date": "1999-07-27", "time": "18:00", "stadium": "Estadio Azteca", "city": "Mexico City" }, { "home_team": "MEX", "away_team": "EGY", "home_score": 2, "away_score": 2, "date": "1999-07-27", "time": "20:30", "stadium": "Estadio Azteca", "city": "Mexico City" }, { "home_team": "EGY", "away_team": "KSA", "home_score": 1, "away_score": 5, "date": "1999-07-29", "time": "18:00", "stadium": "Estadio Azteca", "city": "Mexico City" }, { "home_team": "BOL", "away_team": "MEX", "home_score": 0, "away_score": 1, "date": "1999-07-29", "time": "20:30", "stadium": "Estadio Azteca", "city": "Mexico City" } ] }, { "name": "Group B", "teams": [{ "id": "BRA" }, { "id": "GER" }, { "id": "NZL" }, { "id": "USA" }], "matches": [ { "home_team": "BRA", "away_team": "GER", "home_score": 4, "away_score": 0, "date": "1999-07-24", "time": "12:00", "stadium": "Estadio Jalisco", "city": "Guadalajara" }, { "home_team": "NZL", "away_team": "USA", "home_score": 1, "away_score": 2, "date": "1999-07-24", "time": "14:30", "stadium": "Estadio Jalisco", "city": "Guadalajara" }, { "home_team": "GER", "away_team": "NZL", "home_score": 2, "away_score": 0, "date": "1999-07-28", "time": "18:00", "stadium": "Estadio Jalisco", "city": "Guadalajara" }, { "home_team": "BRA", "away_team": "USA", "home_score": 1, "away_score": 0, "date": "1999-07-28", "time": "20:30", "stadium": "Estadio Jalisco", "city": "Guadalajara" }, { "home_team": "USA", "away_team": "GER", "home_score": 2, "away_score": 0, "date": "1999-07-30", "time": "18:00", "stadium": "Estadio Jalisco", "city": "Guadalajara" }, { "home_team": "NZL", "away_team": "BRA", "home_score": 0, "away_score": 2, "date": "1999-07-30", "time": "20:30", "stadium": "Estadio Jalisco", "city": "Guadalajara" } ] } ] }, { "name": "Knockout Stage", "type": "knockout", "rounds": [ { "name": "Semi-finals", "short_name": "1/2", "eliminateCount": 2, "next_round": "Final", "matches": [ { "home_team": "MEX", "away_team": "USA", "home_score": 0, "away_score": 0, "home_extra_score": 1, "away_extra_score": 0, "date": "1999-08-01", "time": "12:00", "stadium": "Estadio Azteca", "city": "Mexico City", "bracket_order": 1 }, { "home_team": "BRA", "away_team": "KSA", "home_score": 8, "away_score": 2, "date": "1999-08-01", "time": "15:00", "stadium": "Estadio Jalisco", "city": "Guadalajara", "bracket_order": 2 } ] }, { "name": "Third-place", "short_name": "3rd", "matches": [ { "home_team": "USA", "away_team": "KSA", "home_score": 2, "away_score": 0, "date": "1999-08-03", "time": "21:00", "stadium": "Estadio Jalisco", "city": "Guadalajara" } ] }, { "name": "Final", "short_name": "1st", "matches": [ { "home_team": "MEX", "away_team": "BRA", "home_score": 4, "away_score": 3, "date": "1999-08-04", "time": "21:00", "stadium": "Estadio Azteca", "city": "Mexico City" } ] } ] } ] }