{
    "id": "CONFEDC2001",
    "stages": [
        {
            "name": "Group Stage",
            "type": "roundrobin_final",
            "eliminate_count": 4,
            "next_round": "Semi-finals",
            "advancements": {
                "positions": [
                    { "pos": 1, "next": "advance" },
                    { "pos": 2, "next": "advance" }
                ],
                "advanced_notes": "Group winners and runners-up advanced to Knockout stage"
            },
            "groups": [
                {
                    "name": "Group A",
                    "teams": [{ "id": "KOR" }, { "id": "AUS" }, { "id": "FRA" }, { "id": "MEX" }],
                    "matchdays": [
                        {
                            "name": "Matchday 1",
                            "matches": [
                                {
                                    "home_team": "FRA",
                                    "away_team": "KOR",
                                    "home_score": 5,
                                    "away_score": 0,
                                    "date": "2001-05-30",
                                    "time": "17:00",
                                    "stadium": "Daegu World Cup Stadium",
                                    "city": "Daegu"
                                },
                                {
                                    "home_team": "MEX",
                                    "away_team": "AUS",
                                    "home_score": 0,
                                    "away_score": 2,
                                    "date": "2001-05-30",
                                    "time": "19:30",
                                    "stadium": "Suwon World Cup Stadium",
                                    "city": "Suwon"
                                }
                            ]
                        },
                        {
                            "name": "Matchday 2",
                            "matches": [
                                {
                                    "home_team": "AUS",
                                    "away_team": "FRA",
                                    "home_score": 1,
                                    "away_score": 0,
                                    "date": "2001-06-01",
                                    "time": "17:00",
                                    "stadium": "Daegu World Cup Stadium",
                                    "city": "Daegu"
                                },
                                {
                                    "home_team": "KOR",
                                    "away_team": "MEX",
                                    "home_score": 2,
                                    "away_score": 1,
                                    "date": "2001-06-01",
                                    "time": "19:30",
                                    "stadium": "Ulsan Munsu Football Stadium",
                                    "city": "Ulsan"
                                }
                            ]
                        },
                        {
                            "name": "Matchday 3",
                            "matches": [
                                {
                                    "home_team": "FRA",
                                    "away_team": "MEX",
                                    "home_score": 4,
                                    "away_score": 0,
                                    "date": "2001-06-03",
                                    "time": "19:30",
                                    "stadium": "Ulsan Munsu Football Stadium",
                                    "city": "Ulsan"
                                },
                                {
                                    "home_team": "KOR",
                                    "away_team": "AUS",
                                    "home_score": 1,
                                    "away_score": 0,
                                    "date": "2001-06-03",
                                    "time": "19:30",
                                    "stadium": "Suwon World Cup Stadium",
                                    "city": "Suwon"
                                }
                            ]
                        }
                    ]
                },
                {
                    "name": "Group B",
                    "teams": [{ "id": "BRA" }, { "id": "CMR" }, { "id": "JPN" }, { "id": "CAN" }],
                    "matchdays": [
                        {
                            "name": "Matchday 1",
                            "matches": [
                                {
                                    "home_team": "BRA",
                                    "away_team": "CMR",
                                    "home_score": 2,
                                    "away_score": 0,
                                    "date": "2001-05-31",
                                    "time": "17:00",
                                    "stadium": "Kashima Soccer Stadium",
                                    "city": "Ibaraki"
                                },
                                {
                                    "home_team": "JPN",
                                    "away_team": "CAN",
                                    "home_score": 3,
                                    "away_score": 0,
                                    "date": "2001-05-31",
                                    "time": "19:30",
                                    "stadium": "Niigata Stadium",
                                    "city": "Niigata"
                                }
                            ]
                        },
                        {
                            "name": "Matchday 2",
                            "matches": [
                                {
                                    "home_team": "CAN",
                                    "away_team": "BRA",
                                    "home_score": 0,
                                    "away_score": 0,
                                    "date": "2001-06-02",
                                    "time": "17:00",
                                    "stadium": "Kashima Soccer Stadium",
                                    "city": "Ibaraki"
                                },
                                {
                                    "home_team": "CMR",
                                    "away_team": "JPN",
                                    "home_score": 0,
                                    "away_score": 2,
                                    "date": "2001-06-02",
                                    "time": "19:30",
                                    "stadium": "Niigata Stadium",
                                    "city": "Niigata"
                                }
                            ]
                        },
                        {
                            "name": "Matchday 3",
                            "matches": [
                                {
                                    "home_team": "BRA",
                                    "away_team": "JPN",
                                    "home_score": 0,
                                    "away_score": 0,
                                    "date": "2001-06-04",
                                    "time": "19:30",
                                    "stadium": "Kashima Soccer Stadium",
                                    "city": "Ibaraki"
                                },
                                {
                                    "home_team": "CMR",
                                    "away_team": "CAN",
                                    "home_score": 2,
                                    "away_score": 0,
                                    "date": "2001-06-04",
                                    "time": "19:30",
                                    "stadium": "Niigata Stadium",
                                    "city": "Niigata"
                                }
                            ]
                        }
                    ]
                }
            ]
        },
        {
            "name": "Knockout Stage",
            "type": "knockout_",
            "rounds": [
                {
                    "name": "Semi-finals",
                    "short_name": "1/2",
                    "eliminate_count": 2,
                    "next_round": "Final",
                    "matches": [
                        {
                            "home_team": "JPN",
                            "away_team": "AUS",
                            "home_score": 1,
                            "away_score": 0,
                            "date": "2001-06-07",
                            "time": "17:00",
                            "stadium": "International Stadium Yokohama",
                            "city": "Yokohama",
                            "bracket_order": 1
                        },
                        {
                            "home_team": "FRA",
                            "away_team": "BRA",
                            "home_score": 2,
                            "away_score": 1,
                            "date": "2001-06-07",
                            "time": "20:00",
                            "stadium": "Suwon World Cup Stadium",
                            "city": "Suwon",
                            "bracket_order": 2
                        }
                    ]
                },
                {
                    "name": "Final",
                    "short_name": "1st",
                    "final": true,
                    "third_place": true,
                    "championship": true,
                    "matches": [
                        {
                            "home_team": "AUS",
                            "away_team": "BRA",
                            "home_score": 1,
                            "away_score": 0,
                            "date": "2001-06-09",
                            "time": "19:00",
                            "stadium": "Ulsan Munsu Football Stadium",
                            "city": "Ulsan",
                            "third_place": true
                        },
                        {
                            "home_team": "JPN",
                            "away_team": "FRA",
                            "home_score": 0,
                            "away_score": 1,
                            "date": "2001-06-10",
                            "time": "19:00",
                            "stadium": "International Stadium Yokohama",
                            "city": "Yokohama",
                            "final": true
                        }
                    ]
                }
            ]
        }
    ]
}
