{
    "id": "WC2026",
    "year": "2026",
    "name": "FIFA World Cup Canada - Mexico - United States 2026",
    "competition_id": "WC",
    "active": true,
    "points_for_win": 3,
    "details": {
        "host": { "confederation_id": "CONCACAF", "teams": ["CAN", "MEX", "USA"] },
        "logo_filename": "2026_FIFA_World_Cup.svg",
        "start_date": "2026-06-11",
        "end_date": "2026-07-19",
        "color": "#8a1538",
        "team_count": 48,
        "confed_count": 6,
        "venue_count": 16,
        "city_count": 16
    },
    "hero_images": [{ "name": "Ras Abu Aboud Stadium", "filename": "CG_rendering_of_Ras_Abu_Aboud_Stadium_crop.jpg", "text": "Ras Abu Aboud Stadium" }],
    "qualifications": [
        {
            "id": "AFC",
            "draws": [
                { "id": "1", "date": "2023-07-27" },
                { "id": "2", "date": "2024-06-27" }
            ],
            "stages": [
                {
                    "name": "First Round",
                    "type": "pair2leg",
                    "draw_id": "1",
                    "draw_note": "20 teams (ranked 27–46) were divided into Pot 1 and Pot 2 and played home-and-away over two legs. One team from each pot were drawn into one tie. The ten winners advanced to the second round.",
                    "result_note": "Bolded team winners advanced to the second round",
                    "pots": [
                        { "name": 1, "rankingFrom": 27, "rankingTo": 36 },
                        { "name": 2, "rankingFrom": 37, "rankingTo": 46 }
                    ],
                    "matchdays": [
                        { "name": "First leg", "date": "2023-10-12", "matches": [{ "home_pos": 1, "away_pos": 2 }] },
                        { "name": "Second leg", "date": "2023-10-17", "matches": [{ "home_pos": 2, "away_pos": 1 }] }
                    ],
                    "next_stage": "Second Round"
                },
                {
                    "name": "Second Round",
                    "type": "roundrobin2leg",
                    "draw_id": "1",
                    "draw_note": "Total of 36 teams were drawn into nine groups of four to play home-and-away round-robin matches. The 9 winners and 9 runners-up will advance to the 3rd round. 26 teams (ranked 1–26) received byes to this round and were divided into Pot 1, Pot 2 and Pot 3. 10 winners from 1st round go into Pot 4. After 9 teams of Pot 4 were drawn into groups, the last team in Pot 4 will be moved to Pot 3.",
                    "entering_placement": [
                        { "name": 4, "count": 9 },
                        { "name": 3, "count": 1 }
                    ],
                    "pots": [
                        { "name": 1, "rankingFrom": 1, "rankingTo": 9 },
                        { "name": 2, "rankingFrom": 10, "rankingTo": 18 },
                        { "name": 3, "rankingFrom": 19, "rankingTo": 26 }
                    ],
                    "matchdays": [
                        {
                            "name": "Matchday 1",
                            "date": "2023-11-16",
                            "matches": [
                                { "home_pos": 1, "away_pos": 4 },
                                { "home_pos": 3, "away_pos": 2 }
                            ]
                        },
                        {
                            "name": "Matchday 2",
                            "date": "2023-11-21",
                            "matches": [
                                { "home_pos": 4, "away_pos": 3 },
                                { "home_pos": 2, "away_pos": 1 }
                            ]
                        },
                        {
                            "name": "Matchday 3",
                            "date": "2024-03-21",
                            "matches": [
                                { "home_pos": 1, "away_pos": 3 },
                                { "home_pos": 4, "away_pos": 2 }
                            ]
                        },
                        {
                            "name": "Matchday 4",
                            "date": "2024-03-26",
                            "matches": [
                                { "home_pos": 2, "away_pos": 4 },
                                { "home_pos": 3, "away_pos": 1 }
                            ]
                        },
                        {
                            "name": "Matchday 5",
                            "date": "2024-06-06",
                            "matches": [
                                { "home_pos": 4, "away_pos": 1 },
                                { "home_pos": 2, "away_pos": 3 }
                            ]
                        },
                        {
                            "name": "Matchday 6",
                            "date": "2024-06-11",
                            "matches": [
                                { "home_pos": 1, "away_pos": 2 },
                                { "home_pos": 3, "away_pos": 4 }
                            ]
                        }
                    ],
                    "next_stage": "Third Round"
                }
            ]
        }
    ]
}
